{
  "_comment": "A library module in the real schema from spectrumefficiencylimited/power-bi-template (modules/). This is the ER KPI strip — the same five healthcare KPIs the engine generates from config/examples/hospital_er.yaml, with the patient-count contract (DISTINCTCOUNT) and the brand colour baked in. The repo is the source of truth; this mirrors its shape.",
  "module": {
    "name": "ED KPI Strip",
    "type": "kpi_strip",
    "category": "kpi",
    "description": "Top-line ED operating metrics. Drop on any dashboard for a consistent, governed header row.",
    "version": "1.0",
    "author": "Insights and Analytics Unit",
    "created": "2026-05-26",
    "dependencies": ["ER_Data", "Calendar"],
    "measures_required": [
      "Number of Patients",
      "Avg Wait Time (min)",
      "Satisfaction Score",
      "Patients Referred",
      "% Seen < 30 min"
    ],
    "config": {
      "visualType": "kpi_strip",
      "primary_color": "#0066CC",
      "cards": [
        {
          "field": "Patient ID",
          "display_name": "Number of Patients",
          "aggregation": "DISTINCTCOUNT",
          "format": "#,0",
          "contract": "patient_count_distinct (error) — must be DISTINCTCOUNT, never COUNT/COUNTROWS"
        },
        {
          "field": "Patient Wait Time",
          "display_name": "Avg Wait Time (min)",
          "aggregation": "AVERAGE",
          "format": "#,0.0"
        },
        {
          "field": "Patient Satisfaction Score",
          "display_name": "Satisfaction Score",
          "aggregation": "AVERAGE",
          "format": "#,0.0"
        },
        {
          "field": "Department Referral",
          "display_name": "Patients Referred",
          "aggregation": "COUNTROWS_FILTERED",
          "filter_condition": "[Department Referral] <> 'None'",
          "format": "#,0"
        },
        {
          "field": "SLA_Compliance",
          "display_name": "% Seen < 30 min",
          "aggregation": "PERCENTAGE",
          "format": "0.0%",
          "contract": "no_hardcoded_sla (warning) — 30-min threshold + 85% target come from parameters, not the visual"
        }
      ]
    }
  }
}
